{"name": "Adliger_(Frankreich)", "id": 10057228, "predecessors": [{"name": "Adliger", "id": 242773}, {"name": "Adel", "id": 237507}, {"name": "!Hauptkategorie", "id": 235489}], "successors": [{"name": "König_(Frankreich)", "id": 259424}, {"name": "Graf_(Frankreich)", "id": 924193}, {"name": "Herr_(Frankreich)", "id": 4611984}, {"name": "Markgraf_(Frankreich)", "id": 10080876}, {"name": "Hofdame_(Frankreich)", "id": 11579165}, {"name": "Herzog_(Frankreich)", "id": 807689}, {"name": "Pair_von_Frankreich_(Ancien_Régime)", "id": 10591583}, {"name": "Mitglied_der_Pairskammer_(Herrschaft_der_Hundert_Tage)", "id": 10593979}, {"name": "Mitglied_der_Pairskammer_(Restauration)", "id": 10593983}, {"name": "Mitglied_der_Pairskammer_(Julimonarchie)", "id": 10593985}]}