{"name": "Stickstoffverbindung", "id": 1782799, "predecessors": [{"name": "Chemie", "id": 235238}], "successors": [{"name": "Nitrat", "id": 968487}, {"name": "Amin", "id": 1072056}, {"name": "Nitrid", "id": 1782683}, {"name": "Ammoniumverbindung", "id": 2681262}, {"name": "Imin", "id": 4592859}, {"name": "Lactam", "id": 2472290}, {"name": "Stickstoffhaltiger_gesättigter_Heterocyclus", "id": 3191860}, {"name": "Tetrahydroazin", "id": 4111417}, {"name": "Pyrimidin", "id": 2622157}, {"name": "Triazin", "id": 4056316}, {"name": "Pyridin", "id": 5409318}, {"name": "Aminoazin", "id": 5451517}, {"name": "Pyrimidinon", "id": 8351132}, {"name": "Imidazolin", "id": 3711671}, {"name": "Pyrrolin", "id": 5458192}, {"name": "Carbamat", "id": 3351679}, {"name": "Sulfonamid", "id": 3389149}, {"name": "Harnstoff", "id": 3488480}, {"name": "Anilid", "id": 4470720}, {"name": "Carbonsäureamid", "id": 4989145}, {"name": "Hydrazid", "id": 11157128}, {"name": "Nitril", "id": 2672492}, {"name": "Azobenzol", "id": 4470800}, {"name": "Azonaphthalin", "id": 10868591}]}