{"name": "Geschlecht", "id": 253928, "predecessors": [{"name": "!Hauptkategorie", "id": 235489}], "successors": [{"name": "Geschlechterforschung", "id": 1012763}, {"name": "Gender", "id": 11360186}, {"name": "Penis", "id": 1730008}, {"name": "Hoden", "id": 3421711}, {"name": "Gebärmutter", "id": 3421795}, {"name": "Eierstock", "id": 3423602}, {"name": "Vagina", "id": 4235151}, {"name": "Feminismus", "id": 247242}, {"name": "Frau", "id": 271658}, {"name": "Frauengeschichte", "id": 286655}, {"name": "Herzogin", "id": 689921}, {"name": "Frauenkleidung", "id": 959941}, {"name": "Fürstin", "id": 2919731}, {"name": "Mutterschaft", "id": 6700374}, {"name": "Frauen_und_Medien", "id": 7594621}, {"name": "Frauen_und_Politik", "id": 7596114}, {"name": "Frauen_und_Militär", "id": 8324761}, {"name": "Frau_(Bezeichnung)", "id": 8386028}, {"name": "Frauen_(Arbeitswelt)", "id": 9901234}, {"name": "Liste_(Frauenlisten)", "id": 11469794}, {"name": "Frauen_und_Gesundheit", "id": 11485197}, {"name": "Frauensportwettbewerb", "id": 8160848}, {"name": "Mann", "id": 271657}, {"name": "Andrologie", "id": 284393}, {"name": "Männerkleidung", "id": 1154012}, {"name": "Patronym", "id": 4309044}, {"name": "Mann_(Bezeichnung)", "id": 8386046}, {"name": "Frauenverband", "id": 1000844}, {"name": "Feministische_Organisation", "id": 6626305}, {"name": "Christliche_Organisation_(Frauen)", "id": 11169915}, {"name": "Boygroup", "id": 1218154}, {"name": "Männerorden", "id": 1777489}, {"name": "Knabenchor", "id": 2066215}, {"name": "Männerchor", "id": 2097856}, {"name": "Sexismus", "id": 3703989}, {"name": "Frauenfußballverein", "id": 4401875}, {"name": "Frauenhandballverein", "id": 7729047}, {"name": "Fraueneishockeyverein", "id": 9588051}, {"name": "Feministische_Kunst", "id": 8087884}, {"name": "Frauen_und_Musik", "id": 9376798}, {"name": "Frauen_und_Literatur", "id": 10828084}, {"name": "Frauen_und_Film", "id": 11650905}, {"name": "Frauenporträt", "id": 7592897}, {"name": "Weiblicher_Akt", "id": 7596200}, {"name": "Frauendarstellung_(Gemälde)", "id": 9405020}, {"name": "Frauenskulptur", "id": 9690840}, {"name": "Frauenverband_(Deutschland)", "id": 9854660}, {"name": "Handball-Europameisterschaft_der_Frauen", "id": 8447973}, {"name": "Miss_Germany", "id": 1741592}, {"name": "Frauengeschichte_(Deutschland)", "id": 7593488}, {"name": "Frauensport_(Deutschland)", "id": 8068423}, {"name": "Frauenrechte_(Deutschland)", "id": 10537363}, {"name": "Geehrte_des_Projekts_Frauenorte", "id": 10715287}, {"name": "Trägerin_des_Sternkreuzordens", "id": 5530722}, {"name": "Schweizerische_Frauengeschichte", "id": 690341}, {"name": "Frauenverband_(Schweiz)", "id": 6077370}, {"name": "Frauenrechtler_(Österreich)", "id": 11335544}, {"name": "Frauenrechtler_(Schweiz)", "id": 11335511}, {"name": "Weibliche_Gottheit", "id": 6064069}, {"name": "Fiktive_Person_(weiblich)", "id": 7780660}, {"name": "Weibliches_Fabelwesen", "id": 11217248}, {"name": "Männlicher_Akt", "id": 12420340}, {"name": "Frauenförderpreis", "id": 4901613}, {"name": "Handballspieler_(HC_Leipzig)", "id": 8605253}]}