{"name": "Aves", "id": 2724040, "predecessors": [{"name": "Metazoa", "id": 2810730}], "successors": [{"name": "Cuculiformes", "id": 2724193}, {"name": "Charadriiformes", "id": 2724824}, {"name": "Caprimulgidae", "id": 2724849}, {"name": "Columbiformes", "id": 2724854}, {"name": "Passeriformes", "id": 2724862}, {"name": "Falconidae", "id": 2943212}, {"name": "Coraciiformes", "id": 3355756}, {"name": "Strigidae", "id": 3230976}, {"name": "Phasianidae", "id": 2724166}, {"name": "Rallidae", "id": 2897489}, {"name": "Psittaculidae", "id": 12427487}, {"name": "Procellariidae", "id": 4540573}, {"name": "Ardeidae", "id": 3104461}, {"name": "Threskiornithidae", "id": 3106901}, {"name": "Picidae", "id": 3280852}, {"name": "Ramphastidae", "id": 3416872}, {"name": "Lybiidae", "id": 11782302}, {"name": "Arinae", "id": 12427536}, {"name": "Trochilidae", "id": 2724189}, {"name": "Apodidae", "id": 3078964}, {"name": "Bucerotidae", "id": 2724810}, {"name": "Accipitridae", "id": 2724061}, {"name": "Phalacrocoracidae", "id": 6899975}, {"name": "Anatini", "id": 10635631}]}