{"name": "LGBT", "id": 3064392, "predecessors": [{"name": "Gender", "id": 11360186}, {"name": "!Hauptkategorie", "id": 235489}], "successors": [{"name": "Transgeschlechtlichkeit", "id": 241409}, {"name": "Homosexualit채t", "id": 252721}, {"name": "Ex-Gay-Bewegung", "id": 1368920}, {"name": "LGBT-Medium", "id": 1780470}, {"name": "Eunuch", "id": 1808792}, {"name": "LGBT-Aktivist", "id": 1756350}, {"name": "LGBT-Politiker", "id": 12507429}, {"name": "Tr채ger_des_Lambda_Literary_Award", "id": 10744138}, {"name": "LGBT-B체rgerrechtsorganisation", "id": 4538056}, {"name": "LGBT-Organisation_in_Deutschland", "id": 10811157}, {"name": "Tr채ger_des_Stonewall_Book_Award", "id": 11685562}]}