{"name": "Recht_(Schweiz)", "id": 308286, "predecessors": [{"name": "!Hauptkategorie", "id": 235489}], "successors": [{"name": "Rechtsquelle_(Schweiz)", "id": 1115599}, {"name": "Privatrecht_(Schweiz)", "id": 5125045}, {"name": "Öffentliches_Recht_(Schweiz)", "id": 5125064}, {"name": "Rechtsgeschichte_(Schweiz)", "id": 5220522}, {"name": "Strafrecht_(Schweiz)", "id": 5789747}, {"name": "Kantonales_Recht_(Schweiz)", "id": 6442839}, {"name": "Richter_(Schweiz)", "id": 2471125}, {"name": "Rechtsanwalt_(Schweiz)", "id": 3737327}, {"name": "Staatsanwalt_(Schweiz)", "id": 6407492}, {"name": "Notar_(Schweiz)", "id": 8477286}, {"name": "Jurist_im_auswärtigen_Dienst_(Schweiz)", "id": 9148401}, {"name": "Steuerrecht_(Schweiz)", "id": 5569617}, {"name": "Obligationenrecht_(Schweiz)", "id": 5596475}]}