{"name": "Bildung_in_Nordrhein-Westfalen", "id": 4620289, "predecessors": [{"name": "Bildung_in_Deutschland", "id": 2521093}, {"name": "!Hauptkategorie", "id": 235489}], "successors": [{"name": "Hochschullehrer_(Köln)", "id": 1758967}, {"name": "Hochschullehrer_(Witten)", "id": 4636479}, {"name": "Hochschullehrer_(Universität_Duisburg-Essen)", "id": 6637295}, {"name": "Bibliothek_in_Nordrhein-Westfalen", "id": 3042157}, {"name": "Bildungseinrichtung_der_Erwachsenenbildung_in_Nordrhein-Westfalen", "id": 7322472}, {"name": "Gesamtschule_in_Nordrhein-Westfalen", "id": 2563531}, {"name": "Realschule_in_Nordrhein-Westfalen", "id": 3743349}, {"name": "Grundschule_in_Nordrhein-Westfalen", "id": 5685559}, {"name": "Ehemalige_Schule_in_Nordrhein-Westfalen", "id": 8547397}, {"name": "Berufskolleg_in_Nordrhein-Westfalen", "id": 3743315}, {"name": "Hochschullehrer_(PH_Ruhr,_Abteilung_Dortmund)", "id": 6610760}, {"name": "Hochschullehrer_(HfM_Detmold)", "id": 4781103}, {"name": "Hochschullehrer_(Universität_Paderborn)", "id": 4635781}, {"name": "Hochschullehrer_(Theologische_Fakultät_Paderborn)", "id": 4636226}, {"name": "Hochschullehrer_(Universität_Siegen)", "id": 6612644}]}