{"name": "Theaterschaffender", "id": 4995998, "predecessors": [{"name": "Theater", "id": 245755}, {"name": "!Hauptkategorie", "id": 235489}], "successors": [{"name": "Theaterregisseur", "id": 291484}, {"name": "Theaterschauspieler", "id": 350121}, {"name": "Theaterintendant", "id": 706306}, {"name": "Dramaturg", "id": 887039}, {"name": "Kost端mbildner", "id": 1042820}, {"name": "Theaterleiter", "id": 1109086}, {"name": "Maskenbildner", "id": 1294008}, {"name": "B端hnenmaler", "id": 3124713}, {"name": "Theaterproduzent", "id": 5238940}, {"name": "Pantomime_(Darsteller)", "id": 5502591}, {"name": "Theatergr端nder", "id": 8627851}, {"name": "B端hnenautor", "id": 9860429}]}