{"name": "Militärischer_Verband", "id": 556753, "predecessors": [{"name": "!Hauptkategorie", "id": 235489}], "successors": [{"name": "Militärischer_Verband_(multinational)", "id": 557624}, {"name": "Militärischer_Verband_(historisch)", "id": 558575}, {"name": "Liste_(militärische_Verbände)", "id": 11576394}, {"name": "Garde_(Preußen)", "id": 5927821}, {"name": "Pionierverband", "id": 8977539}, {"name": "Verband_der_Panzertruppe", "id": 11416356}, {"name": "Militärischer_Verband_in_den_Koalitionskriegen", "id": 7972972}, {"name": "Militärischer_Verband_im_Russisch-Japanischen_Krieg", "id": 8200922}, {"name": "Militärischer_Verband_im_Deutsch-Französischen_Krieg", "id": 8221101}, {"name": "Militärischer_Verband_im_Zweiten_Japanisch-Chinesischen_Krieg", "id": 8579740}, {"name": "Militärischer_Verband_im_Bürgerkrieg_in_Syrien_seit_2011", "id": 9021806}, {"name": "Militärischer_Verband_im_Siebenjährigen_Krieg", "id": 9884285}, {"name": "Militärischer_Verband_in_den_Jugoslawienkriegen", "id": 12931426}, {"name": "Militärischer_Verband_(Russland)", "id": 556595}, {"name": "Militärischer_Verband_(Rom)", "id": 556652}, {"name": "Militärischer_Verband_(Bundesheer)", "id": 5691005}, {"name": "Militärischer_Großverband_(Italien)", "id": 2650274}, {"name": "Militärischer_Verband_(deutsche_Geschichte)", "id": 1252575}, {"name": "Militärischer_Verband_der_Marine_(Bundeswehr)", "id": 3421739}, {"name": "Militärischer_Verband_der_Luftwaffe_(Bundeswehr)", "id": 3421764}, {"name": "Militärischer_Verband_in_der_Streitkräftebasis_(Bundeswehr)", "id": 3666461}, {"name": "Infanterieverband_(Bundeswehr)", "id": 5999774}, {"name": "Luftlandeverband_(Bundeswehr)", "id": 6022002}, {"name": "Militärischer_Verband_(Geschichte_der_Bundeswehr)", "id": 10630395}, {"name": "Infanterieverband_(deutsche_Geschichte)", "id": 6491264}, {"name": "Brigade_(Deutsches_Kaiserreich)", "id": 11594383}, {"name": "Infanteriebrigade_(Bayern)", "id": 4528412}, {"name": "Division_der_Wehrmacht", "id": 3426268}, {"name": "Division_(United_States_Army)", "id": 7812428}, {"name": "Division_(Kaiserlich_Japanische_Armee)", "id": 8543746}, {"name": "Liste_militärischer_Divisionen_nach_Nummern", "id": 9794268}, {"name": "Division_des_Deutschen_Heeres_im_Ersten_Weltkrieg", "id": 8913492}, {"name": "Division_des_Deutschen_Heeres_(Friedensheer)", "id": 8913498}, {"name": "Regiment_der_Frühen_Neuzeit", "id": 4366762}, {"name": "Französisches_Regiment_im_Algerienkrieg", "id": 10627865}, {"name": "Korps_der_Wehrmacht", "id": 3885417}, {"name": "Korps_des_Deutschen_Heeres_im_Ersten_Weltkrieg", "id": 8913763}, {"name": "Brigade_(Geschichte_der_Bundeswehr)", "id": 11131255}, {"name": "Bataillon_(Geschichte_der_Bundeswehr)", "id": 11131294}, {"name": "Regiment_im_Heer_(Bundeswehr)", "id": 10586537}, {"name": "Verteidigungsbezirkskommando", "id": 10586192}, {"name": "Militärische_Armee_nach_alphanumerischen_Ordnungssystemen", "id": 11512655}]}