{"name": "Kultur_(Sowjetunion)", "id": 775935, "predecessors": [{"name": "Geschichte_(20._Jahrhundert)", "id": 6545911}, {"name": "!Hauptkategorie", "id": 235489}, {"name": "Kulturgeschichte", "id": 460330}], "successors": [{"name": "Träger_des_Leninpreises", "id": 7285154}, {"name": "Sowjetismus", "id": 12657692}, {"name": "Literatur_(Sowjetunion)", "id": 4904682}, {"name": "Musiker_(Sowjetunion)", "id": 8181706}, {"name": "Volkskünstler_der_RSFSR", "id": 6414342}, {"name": "Volkskünstler_der_UdSSR_(Darstellende_Kunst)", "id": 8473421}, {"name": "Volkskünstler_der_USSR", "id": 8523066}, {"name": "Volkskünstler_der_Aserbaidschanischen_Sozialistischen_Sowjetrepublik", "id": 9193151}]}