{"name": "Geographie_(Kanton_Bern)", "id": 952324, "predecessors": [{"name": "Geographie_(Schweiz)", "id": 253097}, {"name": "!Hauptkategorie", "id": 235489}], "successors": [{"name": "Ort_im_Kanton_Bern", "id": 568740}, {"name": "Pass_im_Kanton_Bern", "id": 3212290}, {"name": "Berg_im_Kanton_Bern", "id": 3212299}, {"name": "Tal_im_Kanton_Bern", "id": 3229194}, {"name": "Geographie_(Lauterbrunnen)", "id": 9304568}, {"name": "Geographie_(Innertkirchen)", "id": 11154706}, {"name": "Geographie_(Grindelwald)", "id": 11963480}, {"name": "Geographie_(Guttannen)", "id": 12393549}, {"name": "Berner_Statistischer_Bezirk", "id": 11236248}, {"name": "Berner_Gebräuchliches_Quartier_Stadtteil_IV", "id": 11248277}, {"name": "See_im_Kanton_Bern", "id": 1889506}, {"name": "Fluss_im_Kanton_Bern", "id": 3211655}]}